{"traceEvents":[{"pid":35711,"tid":35711,"ph":"X","ts":1363,"dur":650,"name":"ParseClass","args":{"detail":"Range"}},{"pid":35711,"tid":35711,"ph":"X","ts":2559,"dur":642,"name":"Source","args":{"detail":"/usr/include/features.h"}},{"pid":35711,"tid":35711,"ph":"X","ts":2524,"dur":697,"name":"Source","args":{"detail":"/usr/bin/../lib64/gcc/x86_64-pc-linux-gnu/14.2.1/../../../../include/c++/14.2.1/x86_64-pc-linux-gnu/bits/os_defines.h"}},{"pid":35711,"tid":35711,"ph":"X","ts":2054,"dur":1445,"name":"Source","args":{"detail":"/usr/bin/../lib64/gcc/x86_64-pc-linux-gnu/14.2.1/../../../../include/c++/14.2.1/initializer_list"}},{"pid":35711,"tid":35711,"ph":"X","ts":1361,"dur":2372,"name":"ParseDeclarationOrFunctionDefinition","args":{"detail":"/usr/local/lib/ela/boilerplate.hpp:9:1"}},{"pid":35711,"tid":35711,"ph":"X","ts":3814,"dur":622,"name":"Source","args":{"detail":"/usr/include/stdint.h"}},{"pid":35711,"tid":35711,"ph":"X","ts":3776,"dur":741,"name":"Source","args":{"detail":"/usr/lib/clang/18/include/stdint.h"}},{"pid":35711,"tid":35711,"ph":"X","ts":4777,"dur":15478,"name":"Source","args":{"detail":"/usr/bin/../lib64/gcc/x86_64-pc-linux-gnu/14.2.1/../../../../include/c++/14.2.1/type_traits"}},{"pid":35711,"tid":35711,"ph":"X","ts":20313,"dur":847,"name":"Source","args":{"detail":"/usr/bin/../lib64/gcc/x86_64-pc-linux-gnu/14.2.1/../../../../include/c++/14.2.1/bits/move.h"}},{"pid":35711,"tid":35711,"ph":"X","ts":21198,"dur":1039,"name":"Source","args":{"detail":"/usr/bin/../lib64/gcc/x86_64-pc-linux-gnu/14.2.1/../../../../include/c++/14.2.1/bits/utility.h"}},{"pid":35711,"tid":35711,"ph":"X","ts":22798,"dur":1996,"name":"Source","args":{"detail":"/usr/bin/../lib64/gcc/x86_64-pc-linux-gnu/14.2.1/../../../../include/c++/14.2.1/concepts"}},{"pid":35711,"tid":35711,"ph":"X","ts":24928,"dur":688,"name":"ParseClass","args":{"detail":"std::partial_ordering"}},{"pid":35711,"tid":35711,"ph":"X","ts":24924,"dur":696,"name":"ParseDeclarationOrFunctionDefinition","args":{"detail":"/usr/bin/../lib64/gcc/x86_64-pc-linux-gnu/14.2.1/../../../../include/c++/14.2.1/compare:60:3"}},{"pid":35711,"tid":35711,"ph":"X","ts":25787,"dur":573,"name":"ParseClass","args":{"detail":"std::weak_ordering"}},{"pid":35711,"tid":35711,"ph":"X","ts":25783,"dur":580,"name":"ParseDeclarationOrFunctionDefinition","args":{"detail":"/usr/bin/../lib64/gcc/x86_64-pc-linux-gnu/14.2.1/../../../../include/c++/14.2.1/compare:164:3"}},{"pid":35711,"tid":35711,"ph":"X","ts":26498,"dur":594,"name":"ParseClass","args":{"detail":"std::strong_ordering"}},{"pid":35711,"tid":35711,"ph":"X","ts":26494,"dur":602,"name":"ParseDeclarationOrFunctionDefinition","args":{"detail":"/usr/bin/../lib64/gcc/x86_64-pc-linux-gnu/14.2.1/../../../../include/c++/14.2.1/compare:255:3"}},{"pid":35711,"tid":35711,"ph":"X","ts":29169,"dur":2010,"name":"ParseClass","args":{"detail":"std::__compare::_Strong_order"}},{"pid":35711,"tid":35711,"ph":"X","ts":29166,"dur":2017,"name":"ParseDeclarationOrFunctionDefinition","args":{"detail":"/usr/bin/../lib64/gcc/x86_64-pc-linux-gnu/14.2.1/../../../../include/c++/14.2.1/compare:657:5"}},{"pid":35711,"tid":35711,"ph":"X","ts":22282,"dur":10327,"name":"Source","args":{"detail":"/usr/bin/../lib64/gcc/x86_64-pc-linux-gnu/14.2.1/../../../../include/c++/14.2.1/compare"}},{"pid":35711,"tid":35711,"ph":"X","ts":33513,"dur":1854,"name":"ParseClass","args":{"detail":"std::pair"}},{"pid":35711,"tid":35711,"ph":"X","ts":4757,"dur":32703,"name":"Source","args":{"detail":"/usr/bin/../lib64/gcc/x86_64-pc-linux-gnu/14.2.1/../../../../include/c++/14.2.1/bits/stl_pair.h"}},{"pid":35711,"tid":35711,"ph":"X","ts":37524,"dur":1076,"name":"Source","args":{"detail":"/usr/bin/../lib64/gcc/x86_64-pc-linux-gnu/14.2.1/../../../../include/c++/14.2.1/bits/uses_allocator.h"}},{"pid":35711,"tid":35711,"ph":"X","ts":39261,"dur":1510,"name":"ParseDeclarationOrFunctionDefinition","args":{"detail":"/usr/bin/../lib64/gcc/x86_64-pc-linux-gnu/14.2.1/../../../../include/c++/14.2.1/bits/cpp_type_traits.h:67:1"}},{"pid":35711,"tid":35711,"ph":"X","ts":40845,"dur":866,"name":"Source","args":{"detail":"/usr/bin/../lib64/gcc/x86_64-pc-linux-gnu/14.2.1/../../../../include/c++/14.2.1/bits/iterator_concepts.h"}},{"pid":35711,"tid":35711,"ph":"X","ts":41741,"dur":909,"name":"Source","args":{"detail":"/usr/bin/../lib64/gcc/x86_64-pc-linux-gnu/14.2.1/../../../../include/c++/14.2.1/bits/ranges_cmp.h"}},{"pid":35711,"tid":35711,"ph":"X","ts":40804,"dur":7196,"name":"Source","args":{"detail":"/usr/bin/../lib64/gcc/x86_64-pc-linux-gnu/14.2.1/../../../../include/c++/14.2.1/bits/stl_iterator_base_types.h"}},{"pid":35711,"tid":35711,"ph":"X","ts":39243,"dur":9166,"name":"Source","args":{"detail":"/usr/bin/../lib64/gcc/x86_64-pc-linux-gnu/14.2.1/../../../../include/c++/14.2.1/bits/cpp_type_traits.h"}},{"pid":35711,"tid":35711,"ph":"X","ts":48490,"dur":716,"name":"ParseDeclarationOrFunctionDefinition","args":{"detail":"/usr/bin/../lib64/gcc/x86_64-pc-linux-gnu/14.2.1/../../../../include/c++/14.2.1/ext/type_traits.h:37:1"}},{"pid":35711,"tid":35711,"ph":"X","ts":49251,"dur":661,"name":"Source","args":{"detail":"/usr/bin/../lib64/gcc/x86_64-pc-linux-gnu/14.2.1/../../../../include/c++/14.2.1/new"}},{"pid":35711,"tid":35711,"ph":"X","ts":49925,"dur":737,"name":"ParseDeclarationOrFunctionDefinition","args":{"detail":"/usr/bin/../lib64/gcc/x86_64-pc-linux-gnu/14.2.1/../../../../include/c++/14.2.1/new:50:1"}},{"pid":35711,"tid":35711,"ph":"X","ts":48467,"dur":2523,"name":"Source","args":{"detail":"/usr/bin/../lib64/gcc/x86_64-pc-linux-gnu/14.2.1/../../../../include/c++/14.2.1/ext/type_traits.h"}},{"pid":35711,"tid":35711,"ph":"X","ts":51073,"dur":732,"name":"Source","args":{"detail":"/usr/bin/../lib64/gcc/x86_64-pc-linux-gnu/14.2.1/../../../../include/c++/14.2.1/bits/stl_iterator_base_funcs.h"}},{"pid":35711,"tid":35711,"ph":"X","ts":51048,"dur":1538,"name":"Source","args":{"detail":"/usr/bin/../lib64/gcc/x86_64-pc-linux-gnu/14.2.1/../../../../include/c++/14.2.1/bits/stl_construct.h"}},{"pid":35711,"tid":35711,"ph":"X","ts":52668,"dur":891,"name":"ParseClass","args":{"detail":"std::reverse_iterator"}},{"pid":35711,"tid":35711,"ph":"X","ts":56428,"dur":895,"name":"ParseClass","args":{"detail":"std::move_iterator"}},{"pid":35711,"tid":35711,"ph":"X","ts":58256,"dur":2388,"name":"ParseClass","args":{"detail":"std::common_iterator"}},{"pid":35711,"tid":35711,"ph":"X","ts":61076,"dur":1501,"name":"ParseClass","args":{"detail":"std::counted_iterator"}},{"pid":35711,"tid":35711,"ph":"X","ts":63046,"dur":1611,"name":"ParseClass","args":{"detail":"std::basic_const_iterator"}},{"pid":35711,"tid":35711,"ph":"X","ts":39218,"dur":26019,"name":"Source","args":{"detail":"/usr/bin/../lib64/gcc/x86_64-pc-linux-gnu/14.2.1/../../../../include/c++/14.2.1/bits/stl_iterator.h"}},{"pid":35711,"tid":35711,"ph":"X","ts":65306,"dur":999,"name":"Source","args":{"detail":"/usr/bin/../lib64/gcc/x86_64-pc-linux-gnu/14.2.1/../../../../include/c++/14.2.1/ext/numeric_traits.h"}},{"pid":35711,"tid":35711,"ph":"X","ts":66414,"dur":1962,"name":"Source","args":{"detail":"/usr/bin/../lib64/gcc/x86_64-pc-linux-gnu/14.2.1/../../../../include/c++/14.2.1/numbers"}},{"pid":35711,"tid":35711,"ph":"X","ts":68456,"dur":6660,"name":"ParseClass","args":{"detail":"std::ranges::__detail::__max_size_type"}},{"pid":35711,"tid":35711,"ph":"X","ts":68451,"dur":6673,"name":"ParseDeclarationOrFunctionDefinition","args":{"detail":"/usr/bin/../lib64/gcc/x86_64-pc-linux-gnu/14.2.1/../../../../include/c++/14.2.1/bits/max_size_type.h:59:5"}},{"pid":35711,"tid":35711,"ph":"X","ts":75134,"dur":5010,"name":"ParseClass","args":{"detail":"std::ranges::__detail::__max_diff_type"}},{"pid":35711,"tid":35711,"ph":"X","ts":75126,"dur":5029,"name":"ParseDeclarationOrFunctionDefinition","args":{"detail":"/usr/bin/../lib64/gcc/x86_64-pc-linux-gnu/14.2.1/../../../../include/c++/14.2.1/bits/max_size_type.h:440:5"}},{"pid":35711,"tid":35711,"ph":"X","ts":80300,"dur":586,"name":"ParseClass","args":{"detail":"std::numeric_limits"}},{"pid":35711,"tid":35711,"ph":"X","ts":66347,"dur":14838,"name":"Source","args":{"detail":"/usr/bin/../lib64/gcc/x86_64-pc-linux-gnu/14.2.1/../../../../include/c++/14.2.1/bits/max_size_type.h"}},{"pid":35711,"tid":35711,"ph":"X","ts":83730,"dur":572,"name":"ParseClass","args":{"detail":"std::ranges::__access::_SSize"}},{"pid":35711,"tid":35711,"ph":"X","ts":83725,"dur":579,"name":"ParseDeclarationOrFunctionDefinition","args":{"detail":"/usr/bin/../lib64/gcc/x86_64-pc-linux-gnu/14.2.1/../../../../include/c++/14.2.1/bits/ranges_base.h:365:5"}},{"pid":35711,"tid":35711,"ph":"X","ts":86532,"dur":603,"name":"ParseClass","args":{"detail":"std::ranges::__advance_fn"}},{"pid":35711,"tid":35711,"ph":"X","ts":86528,"dur":609,"name":"ParseDeclarationOrFunctionDefinition","args":{"detail":"/usr/bin/../lib64/gcc/x86_64-pc-linux-gnu/14.2.1/../../../../include/c++/14.2.1/bits/ranges_base.h:817:3"}},{"pid":35711,"tid":35711,"ph":"X","ts":39175,"dur":48988,"name":"Source","args":{"detail":"/usr/bin/../lib64/gcc/x86_64-pc-linux-gnu/14.2.1/../../../../include/c++/14.2.1/bits/ranges_base.h"}},{"pid":35711,"tid":35711,"ph":"X","ts":88400,"dur":936,"name":"ParseClass","args":{"detail":"std::ranges::view_interface"}},{"pid":35711,"tid":35711,"ph":"X","ts":89929,"dur":1382,"name":"ParseClass","args":{"detail":"std::ranges::subrange"}},{"pid":35711,"tid":35711,"ph":"X","ts":39149,"dur":55348,"name":"Source","args":{"detail":"/usr/bin/../lib64/gcc/x86_64-pc-linux-gnu/14.2.1/../../../../include/c++/14.2.1/bits/ranges_util.h"}},{"pid":35711,"tid":35711,"ph":"X","ts":94517,"dur":506,"name":"Source","args":{"detail":"/usr/bin/../lib64/gcc/x86_64-pc-linux-gnu/14.2.1/../../../../include/c++/14.2.1/bits/version.h"}},{"pid":35711,"tid":35711,"ph":"X","ts":95975,"dur":1503,"name":"ParseClass","args":{"detail":"std::_Tuple_impl"}},{"pid":35711,"tid":35711,"ph":"X","ts":97512,"dur":1193,"name":"ParseClass","args":{"detail":"std::_Tuple_impl"}},{"pid":35711,"tid":35711,"ph":"X","ts":98985,"dur":4892,"name":"ParseClass","args":{"detail":"std::tuple"}},{"pid":35711,"tid":35711,"ph":"X","ts":4695,"dur":104241,"name":"Source","args":{"detail":"/usr/bin/../lib64/gcc/x86_64-pc-linux-gnu/14.2.1/../../../../include/c++/14.2.1/tuple"}},{"pid":35711,"tid":35711,"ph":"X","ts":108996,"dur":2294,"name":"Source","args":{"detail":"/usr/bin/../lib64/gcc/x86_64-pc-linux-gnu/14.2.1/../../../../include/c++/14.2.1/bits/functional_hash.h"}},{"pid":35711,"tid":35711,"ph":"X","ts":111783,"dur":1982,"name":"Source","args":{"detail":"/usr/bin/../lib64/gcc/x86_64-pc-linux-gnu/14.2.1/../../../../include/c++/14.2.1/bits/predefined_ops.h"}},{"pid":35711,"tid":35711,"ph":"X","ts":114958,"dur":1207,"name":"ParseFunctionDefinition","args":{"detail":"__countl_zero"}},{"pid":35711,"tid":35711,"ph":"X","ts":113808,"dur":3508,"name":"Source","args":{"detail":"/usr/bin/../lib64/gcc/x86_64-pc-linux-gnu/14.2.1/../../../../include/c++/14.2.1/bit"}},{"pid":35711,"tid":35711,"ph":"X","ts":111334,"dur":13600,"name":"Source","args":{"detail":"/usr/bin/../lib64/gcc/x86_64-pc-linux-gnu/14.2.1/../../../../include/c++/14.2.1/bits/stl_algobase.h"}},{"pid":35711,"tid":35711,"ph":"X","ts":125628,"dur":516,"name":"ParseClass","args":{"detail":"std::__new_allocator"}},{"pid":35711,"tid":35711,"ph":"X","ts":125594,"dur":555,"name":"Source","args":{"detail":"/usr/bin/../lib64/gcc/x86_64-pc-linux-gnu/14.2.1/../../../../include/c++/14.2.1/bits/new_allocator.h"}},{"pid":35711,"tid":35711,"ph":"X","ts":125574,"dur":602,"name":"Source","args":{"detail":"/usr/bin/../lib64/gcc/x86_64-pc-linux-gnu/14.2.1/../../../../include/c++/14.2.1/x86_64-pc-linux-gnu/bits/c++allocator.h"}},{"pid":35711,"tid":35711,"ph":"X","ts":125548,"dur":1702,"name":"Source","args":{"detail":"/usr/bin/../lib64/gcc/x86_64-pc-linux-gnu/14.2.1/../../../../include/c++/14.2.1/bits/allocator.h"}},{"pid":35711,"tid":35711,"ph":"X","ts":127484,"dur":1148,"name":"ParseClass","args":{"detail":"std::allocator_traits"}},{"pid":35711,"tid":35711,"ph":"X","ts":125427,"dur":4857,"name":"Source","args":{"detail":"/usr/bin/../lib64/gcc/x86_64-pc-linux-gnu/14.2.1/../../../../include/c++/14.2.1/bits/alloc_traits.h"}},{"pid":35711,"tid":35711,"ph":"X","ts":125388,"dur":5413,"name":"Source","args":{"detail":"/usr/bin/../lib64/gcc/x86_64-pc-linux-gnu/14.2.1/../../../../include/c++/14.2.1/ext/alloc_traits.h"}},{"pid":35711,"tid":35711,"ph":"X","ts":134033,"dur":1357,"name":"InstantiateClass","args":{"detail":"std::pair<bool, unsigned long>"}},{"pid":35711,"tid":35711,"ph":"X","ts":133545,"dur":3241,"name":"ParseClass","args":{"detail":"std::__detail::_Power2_rehash_policy"}},{"pid":35711,"tid":35711,"ph":"X","ts":133537,"dur":3254,"name":"ParseDeclarationOrFunctionDefinition","args":{"detail":"/usr/bin/../lib64/gcc/x86_64-pc-linux-gnu/14.2.1/../../../../include/c++/14.2.1/bits/hashtable_policy.h:624:3"}},{"pid":35711,"tid":35711,"ph":"X","ts":137809,"dur":504,"name":"ParseClass","args":{"detail":"std::__detail::_Insert_base"}},{"pid":35711,"tid":35711,"ph":"X","ts":139622,"dur":521,"name":"ParseClass","args":{"detail":"std::__detail::_Hash_code_base"}},{"pid":35711,"tid":35711,"ph":"X","ts":4675,"dur":138659,"name":"Source","args":{"detail":"/usr/bin/../lib64/gcc/x86_64-pc-linux-gnu/14.2.1/../../../../include/c++/14.2.1/bits/hashtable_policy.h"}},{"pid":35711,"tid":35711,"ph":"X","ts":143401,"dur":1627,"name":"Source","args":{"detail":"/usr/bin/../lib64/gcc/x86_64-pc-linux-gnu/14.2.1/../../../../include/c++/14.2.1/bits/enable_special_members.h"}},{"pid":35711,"tid":35711,"ph":"X","ts":147143,"dur":682,"name":"ParseClass","args":{"detail":"std::greater"}},{"pid":35711,"tid":35711,"ph":"X","ts":147842,"dur":573,"name":"ParseClass","args":{"detail":"std::less"}},{"pid":35711,"tid":35711,"ph":"X","ts":148429,"dur":532,"name":"ParseClass","args":{"detail":"std::greater_equal"}},{"pid":35711,"tid":35711,"ph":"X","ts":148976,"dur":517,"name":"ParseClass","args":{"detail":"std::less_equal"}},{"pid":35711,"tid":35711,"ph":"X","ts":145075,"dur":8589,"name":"Source","args":{"detail":"/usr/bin/../lib64/gcc/x86_64-pc-linux-gnu/14.2.1/../../../../include/c++/14.2.1/bits/stl_function.h"}},{"pid":35711,"tid":35711,"ph":"X","ts":153725,"dur":511,"name":"Source","args":{"detail":"/usr/bin/../lib64/gcc/x86_64-pc-linux-gnu/14.2.1/../../../../include/c++/14.2.1/bits/version.h"}},{"pid":35711,"tid":35711,"ph":"X","ts":154289,"dur":888,"name":"ParseClass","args":{"detail":"std::_Node_handle_common"}},{"pid":35711,"tid":35711,"ph":"X","ts":155199,"dur":541,"name":"ParseClass","args":{"detail":"std::_Node_handle"}},{"pid":35711,"tid":35711,"ph":"X","ts":153708,"dur":2363,"name":"Source","args":{"detail":"/usr/bin/../lib64/gcc/x86_64-pc-linux-gnu/14.2.1/../../../../include/c++/14.2.1/bits/node_handle.h"}},{"pid":35711,"tid":35711,"ph":"X","ts":156187,"dur":4309,"name":"ParseClass","args":{"detail":"std::_Hashtable"}},{"pid":35711,"tid":35711,"ph":"X","ts":4614,"dur":163018,"name":"Source","args":{"detail":"/usr/bin/../lib64/gcc/x86_64-pc-linux-gnu/14.2.1/../../../../include/c++/14.2.1/bits/hashtable.h"}},{"pid":35711,"tid":35711,"ph":"X","ts":167937,"dur":2284,"name":"ParseClass","args":{"detail":"std::unordered_map"}},{"pid":35711,"tid":35711,"ph":"X","ts":170566,"dur":769,"name":"InstantiateClass","args":{"detail":"std::__and_<std::__is_invocable<const std::hash<int> &, const int &>, std::__call_is_nothrow<std::__invoke_result<const std::hash<int> &, const int &>, const std::hash<int> &, const int &>>"}},{"pid":35711,"tid":35711,"ph":"X","ts":170545,"dur":795,"name":"InstantiateClass","args":{"detail":"std::__is_nothrow_invocable<const std::hash<int> &, const int &>"}},{"pid":35711,"tid":35711,"ph":"X","ts":170477,"dur":949,"name":"InstantiateClass","args":{"detail":"std::__and_<std::__is_fast_hash<std::hash<int>>, std::__is_nothrow_invocable<const std::hash<int> &, const int &>>"}},{"pid":35711,"tid":35711,"ph":"X","ts":170472,"dur":979,"name":"InstantiateClass","args":{"detail":"std::__not_<std::__and_<std::__is_fast_hash<std::hash<int>>, std::__is_nothrow_invocable<const std::hash<int> &, const int &>>>"}},{"pid":35711,"tid":35711,"ph":"X","ts":171538,"dur":519,"name":"InstantiateClass","args":{"detail":"std::__detail::_Hashtable_base<int, std::pair<const int, int>, std::__detail::_Select1st, std::equal_to<int>, std::hash<int>, std::__detail::_Mod_range_hashing, std::__detail::_Default_ranged_hash, std::__detail::_Hashtable_traits<false, false, true>>"}},{"pid":35711,"tid":35711,"ph":"X","ts":172513,"dur":873,"name":"InstantiateClass","args":{"detail":"std::__detail::_Hashtable_alloc<std::allocator<std::__detail::_Hash_node<std::pair<const int, int>, false>>>"}},{"pid":35711,"tid":35711,"ph":"X","ts":172196,"dur":1332,"name":"InstantiateClass","args":{"detail":"std::__detail::_Insert_base<int, std::pair<const int, int>, std::allocator<std::pair<const int, int>>, std::__detail::_Select1st, std::equal_to<int>, std::hash<int>, std::__detail::_Mod_range_hashing, std::__detail::_Default_ranged_hash, std::__detail::_Prime_rehash_policy, std::__detail::_Hashtable_traits<false, false, true>>"}},{"pid":35711,"tid":35711,"ph":"X","ts":172183,"dur":1435,"name":"InstantiateClass","args":{"detail":"std::__detail::_Insert<int, std::pair<const int, int>, std::allocator<std::pair<const int, int>>, std::__detail::_Select1st, std::equal_to<int>, std::hash<int>, std::__detail::_Mod_range_hashing, std::__detail::_Default_ranged_hash, std::__detail::_Prime_rehash_policy, std::__detail::_Hashtable_traits<false, false, true>>"}},{"pid":35711,"tid":35711,"ph":"X","ts":173822,"dur":545,"name":"InstantiateClass","args":{"detail":"std::is_default_constructible<std::equal_to<int>>"}},{"pid":35711,"tid":35711,"ph":"X","ts":173807,"dur":1521,"name":"InstantiateClass","args":{"detail":"std::__and_<std::is_default_constructible<std::equal_to<int>>, std::is_default_constructible<std::hash<int>>, std::is_default_constructible<std::allocator<std::pair<const int, int>>>>"}},{"pid":35711,"tid":35711,"ph":"X","ts":171526,"dur":6965,"name":"InstantiateClass","args":{"detail":"std::_Hashtable<int, std::pair<const int, int>, std::allocator<std::pair<const int, int>>, std::__detail::_Select1st, std::equal_to<int>, std::hash<int>, std::__detail::_Mod_range_hashing, std::__detail::_Default_ranged_hash, std::__detail::_Prime_rehash_policy, std::__detail::_Hashtable_traits<false, false, true>>"}},{"pid":35711,"tid":35711,"ph":"X","ts":170445,"dur":8766,"name":"InstantiateClass","args":{"detail":"std::unordered_map<int, int>"}},{"pid":35711,"tid":35711,"ph":"X","ts":182005,"dur":2280,"name":"ParseClass","args":{"detail":"std::unordered_multimap"}},{"pid":35711,"tid":35711,"ph":"X","ts":184568,"dur":2508,"name":"InstantiateClass","args":{"detail":"std::_Hashtable<int, std::pair<const int, int>, std::allocator<std::pair<const int, int>>, std::__detail::_Select1st, std::equal_to<int>, std::hash<int>, std::__detail::_Mod_range_hashing, std::__detail::_Default_ranged_hash, std::__detail::_Prime_rehash_policy, std::__detail::_Hashtable_traits<false, false, false>>"}},{"pid":35711,"tid":35711,"ph":"X","ts":184498,"dur":3112,"name":"InstantiateClass","args":{"detail":"std::unordered_multimap<int, int>"}},{"pid":35711,"tid":35711,"ph":"X","ts":4594,"dur":185630,"name":"Source","args":{"detail":"/usr/bin/../lib64/gcc/x86_64-pc-linux-gnu/14.2.1/../../../../include/c++/14.2.1/bits/unordered_map.h"}},{"pid":35711,"tid":35711,"ph":"X","ts":190309,"dur":1993,"name":"Source","args":{"detail":"/usr/bin/../lib64/gcc/x86_64-pc-linux-gnu/14.2.1/../../../../include/c++/14.2.1/bits/range_access.h"}},{"pid":35711,"tid":35711,"ph":"X","ts":193824,"dur":1664,"name":"ParseDeclarationOrFunctionDefinition","args":{"detail":"/usr/bin/../lib64/gcc/x86_64-pc-linux-gnu/14.2.1/../../../../include/c++/14.2.1/cstddef:55:1"}},{"pid":35711,"tid":35711,"ph":"X","ts":193019,"dur":4165,"name":"Source","args":{"detail":"/usr/bin/../lib64/gcc/x86_64-pc-linux-gnu/14.2.1/../../../../include/c++/14.2.1/cstddef"}},{"pid":35711,"tid":35711,"ph":"X","ts":197672,"dur":767,"name":"ParseClass","args":{"detail":"std::pmr::polymorphic_allocator"}},{"pid":35711,"tid":35711,"ph":"X","ts":192976,"dur":5839,"name":"Source","args":{"detail":"/usr/bin/../lib64/gcc/x86_64-pc-linux-gnu/14.2.1/../../../../include/c++/14.2.1/bits/memory_resource.h"}},{"pid":35711,"tid":35711,"ph":"X","ts":4537,"dur":194575,"name":"Source","args":{"detail":"/usr/bin/../lib64/gcc/x86_64-pc-linux-gnu/14.2.1/../../../../include/c++/14.2.1/unordered_map"}},{"pid":35711,"tid":35711,"ph":"X","ts":199904,"dur":743,"name":"ParseClass","args":{"detail":"_array"}},{"pid":35711,"tid":35711,"ph":"X","ts":201284,"dur":502,"name":"InstantiateFunction","args":{"detail":"std::__niter_base<char *>"}},{"pid":35711,"tid":35711,"ph":"X","ts":201883,"dur":525,"name":"InstantiateFunction","args":{"detail":"std::__copy_move_a1<false, char *, char *>"}},{"pid":35711,"tid":35711,"ph":"X","ts":201253,"dur":1210,"name":"InstantiateFunction","args":{"detail":"std::__copy_move_a<false, char *, char *>"}},{"pid":35711,"tid":35711,"ph":"X","ts":201064,"dur":1408,"name":"InstantiateFunction","args":{"detail":"std::copy<char *, char *>"}},{"pid":35711,"tid":35711,"ph":"X","ts":200658,"dur":3637,"name":"ParseClass","args":{"detail":"string"}},{"pid":35711,"tid":35711,"ph":"X","ts":200653,"dur":3647,"name":"ParseDeclarationOrFunctionDefinition","args":{"detail":"/usr/local/lib/ela/boilerplate.hpp:335:1"}},{"pid":35711,"tid":35711,"ph":"X","ts":1154,"dur":203965,"name":"Source","args":{"detail":"/usr/local/lib/ela/boilerplate.hpp"}},{"pid":35711,"tid":35711,"ph":"X","ts":207690,"dur":784,"name":"ParseFunctionDefinition","args":{"detail":"to_string"}},{"pid":35711,"tid":35711,"ph":"X","ts":207678,"dur":796,"name":"ParseDeclarationOrFunctionDefinition","args":{"detail":"main.cpp:106:1"}},{"pid":35711,"tid":35711,"ph":"X","ts":208476,"dur":556,"name":"CodeGen Function","args":{"detail":"to_string"}},{"pid":35711,"tid":35711,"ph":"X","ts":211295,"dur":600,"name":"ParseFunctionDefinition","args":{"detail":"split"}},{"pid":35711,"tid":35711,"ph":"X","ts":211265,"dur":631,"name":"ParseDeclarationOrFunctionDefinition","args":{"detail":"main.cpp:241:1"}},{"pid":35711,"tid":35711,"ph":"X","ts":214951,"dur":554,"name":"ParseClass","args":{"detail":"Vector2"}},{"pid":35711,"tid":35711,"ph":"X","ts":214949,"dur":559,"name":"ParseDeclarationOrFunctionDefinition","args":{"detail":"main.cpp:433:1"}},{"pid":35711,"tid":35711,"ph":"X","ts":215579,"dur":592,"name":"ParseClass","args":{"detail":"Vector3"}},{"pid":35711,"tid":35711,"ph":"X","ts":215575,"dur":599,"name":"ParseDeclarationOrFunctionDefinition","args":{"detail":"main.cpp:475:1"}},{"pid":35711,"tid":35711,"ph":"X","ts":221530,"dur":544,"name":"ParseFunctionDefinition","args":{"detail":"draw_button"}},{"pid":35711,"tid":35711,"ph":"X","ts":221511,"dur":563,"name":"ParseDeclarationOrFunctionDefinition","args":{"detail":"main.cpp:795:1"}},{"pid":35711,"tid":35711,"ph":"X","ts":222076,"dur":580,"name":"CodeGen Function","args":{"detail":"draw_button"}},{"pid":35711,"tid":35711,"ph":"X","ts":222856,"dur":1277,"name":"ParseClass","args":{"detail":"SliderF"}},{"pid":35711,"tid":35711,"ph":"X","ts":222852,"dur":1284,"name":"ParseDeclarationOrFunctionDefinition","args":{"detail":"main.cpp:847:1"}},{"pid":35711,"tid":35711,"ph":"X","ts":224148,"dur":1201,"name":"ParseClass","args":{"detail":"SliderI"}},{"pid":35711,"tid":35711,"ph":"X","ts":224144,"dur":1207,"name":"ParseDeclarationOrFunctionDefinition","args":{"detail":"main.cpp:902:1"}},{"pid":35711,"tid":35711,"ph":"X","ts":225366,"dur":505,"name":"ParseClass","args":{"detail":"CheckButton"}},{"pid":35711,"tid":35711,"ph":"X","ts":225359,"dur":514,"name":"ParseDeclarationOrFunctionDefinition","args":{"detail":"main.cpp:960:1"}},{"pid":35711,"tid":35711,"ph":"X","ts":225885,"dur":1112,"name":"ParseClass","args":{"detail":"DropDown"}},{"pid":35711,"tid":35711,"ph":"X","ts":225881,"dur":1118,"name":"ParseDeclarationOrFunctionDefinition","args":{"detail":"main.cpp:997:1"}},{"pid":35711,"tid":35711,"ph":"X","ts":232106,"dur":1306,"name":"ParseClass","args":{"detail":"SequenceChannel"}},{"pid":35711,"tid":35711,"ph":"X","ts":232100,"dur":1317,"name":"ParseDeclarationOrFunctionDefinition","args":{"detail":"main.cpp:1160:1"}},{"pid":35711,"tid":35711,"ph":"X","ts":235005,"dur":1403,"name":"ParseFunctionDefinition","args":{"detail":"main"}},{"pid":35711,"tid":35711,"ph":"X","ts":235002,"dur":1407,"name":"ParseDeclarationOrFunctionDefinition","args":{"detail":"main.cpp:1236:1"}},{"pid":35711,"tid":35711,"ph":"X","ts":236411,"dur":991,"name":"CodeGen Function","args":{"detail":"main"}},{"pid":35711,"tid":35711,"ph":"X","ts":237856,"dur":507,"name":"InstantiateFunction","args":{"detail":"std::__niter_base<string *>"}},{"pid":35711,"tid":35711,"ph":"X","ts":237830,"dur":1148,"name":"InstantiateFunction","args":{"detail":"std::__copy_move_a<true, string *, string *>"}},{"pid":35711,"tid":35711,"ph":"X","ts":237717,"dur":1270,"name":"InstantiateFunction","args":{"detail":"std::move<string *, string *>"}},{"pid":35711,"tid":35711,"ph":"X","ts":237637,"dur":1403,"name":"InstantiateFunction","args":{"detail":"_array<string>::resize"}},{"pid":35711,"tid":35711,"ph":"X","ts":237590,"dur":1453,"name":"InstantiateFunction","args":{"detail":"_array<string>::push"}},{"pid":35711,"tid":35711,"ph":"X","ts":239411,"dur":1581,"name":"InstantiateFunction","args":{"detail":"std::__copy_move_a<false, const Color *, Color *>"}},{"pid":35711,"tid":35711,"ph":"X","ts":239278,"dur":1723,"name":"InstantiateFunction","args":{"detail":"std::copy<const Color *, Color *>"}},{"pid":35711,"tid":35711,"ph":"X","ts":239092,"dur":1975,"name":"InstantiateFunction","args":{"detail":"_array<Color>::_array"}},{"pid":35711,"tid":35711,"ph":"X","ts":241420,"dur":917,"name":"InstantiateFunction","args":{"detail":"std::__copy_move_a<false, const string *, string *>"}},{"pid":35711,"tid":35711,"ph":"X","ts":241294,"dur":1052,"name":"InstantiateFunction","args":{"detail":"std::copy<const string *, string *>"}},{"pid":35711,"tid":35711,"ph":"X","ts":241131,"dur":1252,"name":"InstantiateFunction","args":{"detail":"_array<string>::_array"}},{"pid":35711,"tid":35711,"ph":"X","ts":242385,"dur":541,"name":"InstantiateFunction","args":{"detail":"_array<string>::_array"}},{"pid":35711,"tid":35711,"ph":"X","ts":243378,"dur":529,"name":"InstantiateFunction","args":{"detail":"std::__niter_base<CheckButton *>"}},{"pid":35711,"tid":35711,"ph":"X","ts":243353,"dur":1145,"name":"InstantiateFunction","args":{"detail":"std::__copy_move_a<true, CheckButton *, CheckButton *>"}},{"pid":35711,"tid":35711,"ph":"X","ts":243250,"dur":1256,"name":"InstantiateFunction","args":{"detail":"std::move<CheckButton *, CheckButton *>"}},{"pid":35711,"tid":35711,"ph":"X","ts":243131,"dur":1423,"name":"InstantiateFunction","args":{"detail":"_array<CheckButton>::resize"}},{"pid":35711,"tid":35711,"ph":"X","ts":242999,"dur":1555,"name":"InstantiateFunction","args":{"detail":"_array<CheckButton>::push"}},{"pid":35711,"tid":35711,"ph":"X","ts":244839,"dur":544,"name":"InstantiateFunction","args":{"detail":"_array<CheckButton>::_array"}},{"pid":35711,"tid":35711,"ph":"X","ts":244691,"dur":693,"name":"InstantiateFunction","args":{"detail":"_array<SequenceChannel>::pop"}},{"pid":35711,"tid":35711,"ph":"X","ts":246248,"dur":526,"name":"InstantiateFunction","args":{"detail":"std::__copy_move_a1<true, SequenceChannel *, SequenceChannel *>"}},{"pid":35711,"tid":35711,"ph":"X","ts":245678,"dur":1155,"name":"InstantiateFunction","args":{"detail":"std::__copy_move_a<true, SequenceChannel *, SequenceChannel *>"}},{"pid":35711,"tid":35711,"ph":"X","ts":245594,"dur":1248,"name":"InstantiateFunction","args":{"detail":"std::move<SequenceChannel *, SequenceChannel *>"}},{"pid":35711,"tid":35711,"ph":"X","ts":245519,"dur":1452,"name":"InstantiateFunction","args":{"detail":"_array<SequenceChannel>::resize"}},{"pid":35711,"tid":35711,"ph":"X","ts":245385,"dur":1726,"name":"InstantiateFunction","args":{"detail":"_array<SequenceChannel>::push"}},{"pid":35711,"tid":35711,"ph":"X","ts":237412,"dur":9699,"name":"PerformPendingInstantiations"},{"pid":35711,"tid":35711,"ph":"X","ts":887,"dur":246309,"name":"Frontend"},{"pid":35711,"tid":35711,"ph":"X","ts":250147,"dur":562,"name":"CodeGen Function","args":{"detail":"SequenceChannel::SequenceChannel"}},{"pid":35711,"tid":35711,"ph":"X","ts":251529,"dur":575,"name":"CodeGen Function","args":{"detail":"SliderF::draw"}},{"pid":35711,"tid":35711,"ph":"X","ts":252421,"dur":554,"name":"CodeGen Function","args":{"detail":"SliderI::draw"}},{"pid":35711,"tid":35711,"ph":"X","ts":255202,"dur":568,"name":"CodeGen Function","args":{"detail":"DropDown::draw"}},{"pid":35711,"tid":35711,"ph":"X","ts":261421,"dur":663,"name":"CodeGen Function","args":{"detail":"_array<CheckButton>::operator="}},{"pid":35711,"tid":35711,"ph":"X","ts":247197,"dur":15460,"name":"Frontend"},{"pid":35711,"tid":35711,"ph":"X","ts":264257,"dur":829,"name":"AlwaysInlinerPass","args":{"detail":"[module]"}},{"pid":35711,"tid":35711,"ph":"X","ts":264253,"dur":1052,"name":"Optimizer"},{"pid":35711,"tid":35711,"ph":"X","ts":266107,"dur":533,"name":"OptFunction","args":{"detail":"_Z15str_starts_withPcS_"}},{"pid":35711,"tid":35711,"ph":"X","ts":266959,"dur":596,"name":"RunPass","args":{"detail":"X86 DAG->DAG Instruction Selection"}},{"pid":35711,"tid":35711,"ph":"X","ts":266900,"dur":989,"name":"OptFunction","args":{"detail":"_Z11str_replace6stringS_S_"}},{"pid":35711,"tid":35711,"ph":"X","ts":269126,"dur":566,"name":"OptFunction","args":{"detail":"_Z13string_substrPcii"}},{"pid":35711,"tid":35711,"ph":"X","ts":269693,"dur":618,"name":"OptFunction","args":{"detail":"_Z9to_stringl"}},{"pid":35711,"tid":35711,"ph":"X","ts":273257,"dur":685,"name":"RunPass","args":{"detail":"X86 DAG->DAG Instruction Selection"}},{"pid":35711,"tid":35711,"ph":"X","ts":273204,"dur":1084,"name":"OptFunction","args":{"detail":"_Z5split6stringc"}},{"pid":35711,"tid":35711,"ph":"X","ts":275665,"dur":506,"name":"OptFunction","args":{"detail":"_Z10color_lerp5ColorS_f"}},{"pid":35711,"tid":35711,"ph":"X","ts":276205,"dur":648,"name":"RunPass","args":{"detail":"X86 DAG->DAG Instruction Selection"}},{"pid":35711,"tid":35711,"ph":"X","ts":276171,"dur":850,"name":"OptFunction","args":{"detail":"__cxx_global_var_init"}},{"pid":35711,"tid":35711,"ph":"X","ts":277928,"dur":612,"name":"OptFunction","args":{"detail":"_Z11jiggly_textPc9Rectangle5Style"}},{"pid":35711,"tid":35711,"ph":"X","ts":278598,"dur":982,"name":"RunPass","args":{"detail":"X86 DAG->DAG Instruction Selection"}},{"pid":35711,"tid":35711,"ph":"X","ts":278541,"dur":1381,"name":"OptFunction","args":{"detail":"_Z11draw_buttonPc9Rectangle5StylePFvvE"}},{"pid":35711,"tid":35711,"ph":"X","ts":279923,"dur":674,"name":"OptFunction","args":{"detail":"_Z14directory_openPc"}},{"pid":35711,"tid":35711,"ph":"X","ts":280702,"dur":545,"name":"OptFunction","args":{"detail":"_ZN6_arrayI6stringEC2ESt16initializer_listIS0_E"}},{"pid":35711,"tid":35711,"ph":"X","ts":285426,"dur":522,"name":"OptFunction","args":{"detail":"_Z19get_sequencer_style5Style"}},{"pid":35711,"tid":35711,"ph":"X","ts":287471,"dur":748,"name":"OptFunction","args":{"detail":"_Z16on_file_selectedi"}},{"pid":35711,"tid":35711,"ph":"X","ts":288666,"dur":840,"name":"RunPass","args":{"detail":"X86 DAG->DAG Instruction Selection"}},{"pid":35711,"tid":35711,"ph":"X","ts":288622,"dur":1150,"name":"OptFunction","args":{"detail":"_ZN15SequenceChannelC2E5Sound5Style6string"}},{"pid":35711,"tid":35711,"ph":"X","ts":290963,"dur":2402,"name":"RunPass","args":{"detail":"X86 DAG->DAG Instruction Selection"}},{"pid":35711,"tid":35711,"ph":"X","ts":290868,"dur":3316,"name":"OptFunction","args":{"detail":"main"}},{"pid":35711,"tid":35711,"ph":"X","ts":294932,"dur":1283,"name":"RunPass","args":{"detail":"X86 DAG->DAG Instruction Selection"}},{"pid":35711,"tid":35711,"ph":"X","ts":294858,"dur":1893,"name":"OptFunction","args":{"detail":"_ZN7SliderF4drawEv"}},{"pid":35711,"tid":35711,"ph":"X","ts":296836,"dur":1285,"name":"RunPass","args":{"detail":"X86 DAG->DAG Instruction Selection"}},{"pid":35711,"tid":35711,"ph":"X","ts":296751,"dur":1869,"name":"OptFunction","args":{"detail":"_ZN7SliderI4drawEv"}},{"pid":35711,"tid":35711,"ph":"X","ts":298621,"dur":793,"name":"OptFunction","args":{"detail":"_ZN15SequenceChannel4drawEff"}},{"pid":35711,"tid":35711,"ph":"X","ts":299492,"dur":1230,"name":"RunPass","args":{"detail":"X86 DAG->DAG Instruction Selection"}},{"pid":35711,"tid":35711,"ph":"X","ts":299415,"dur":1790,"name":"OptFunction","args":{"detail":"_ZN8DropDown4drawEv"}},{"pid":35711,"tid":35711,"ph":"X","ts":305406,"dur":668,"name":"RunPass","args":{"detail":"X86 DAG->DAG Instruction Selection"}},{"pid":35711,"tid":35711,"ph":"X","ts":305353,"dur":1038,"name":"OptFunction","args":{"detail":"_ZN11CheckButton4drawEv"}},{"pid":35711,"tid":35711,"ph":"X","ts":265608,"dur":57986,"name":"OptModule","args":{"detail":"main.cpp"}},{"pid":35711,"tid":35711,"ph":"X","ts":265606,"dur":58735,"name":"CodeGenPasses"},{"pid":35711,"tid":35711,"ph":"X","ts":264138,"dur":60299,"name":"Backend"},{"pid":35711,"tid":35711,"ph":"X","ts":5,"dur":324537,"name":"ExecuteCompiler"},{"pid":35711,"tid":35712,"ph":"X","ts":0,"dur":324536,"name":"Total ExecuteCompiler","args":{"count":1,"avg ms":324}},{"pid":35711,"tid":35713,"ph":"X","ts":0,"dur":261769,"name":"Total Frontend","args":{"count":2,"avg ms":130}},{"pid":35711,"tid":35714,"ph":"X","ts":0,"dur":203965,"name":"Total Source","args":{"count":1,"avg ms":203}},{"pid":35711,"tid":35715,"ph":"X","ts":0,"dur":111565,"name":"Total ParseClass","args":{"count":956,"avg ms":0}},{"pid":35711,"tid":35716,"ph":"X","ts":0,"dur":69361,"name":"Total ParseDeclarationOrFunctionDefinition","args":{"count":715,"avg ms":0}},{"pid":35711,"tid":35717,"ph":"X","ts":0,"dur":60299,"name":"Total Backend","args":{"count":1,"avg ms":60}},{"pid":35711,"tid":35718,"ph":"X","ts":0,"dur":58734,"name":"Total CodeGenPasses","args":{"count":1,"avg ms":58}},{"pid":35711,"tid":35719,"ph":"X","ts":0,"dur":57985,"name":"Total OptModule","args":{"count":1,"avg ms":57}},{"pid":35711,"tid":35720,"ph":"X","ts":0,"dur":52911,"name":"Total OptFunction","args":{"count":202,"avg ms":0}},{"pid":35711,"tid":35721,"ph":"X","ts":0,"dur":51050,"name":"Total RunPass","args":{"count":14342,"avg ms":0}},{"pid":35711,"tid":35722,"ph":"X","ts":0,"dur":30021,"name":"Total ParseFunctionDefinition","args":{"count":512,"avg ms":0}},{"pid":35711,"tid":35723,"ph":"X","ts":0,"dur":22142,"name":"Total CodeGen Function","args":{"count":223,"avg ms":0}},{"pid":35711,"tid":35724,"ph":"X","ts":0,"dur":21998,"name":"Total InstantiateClass","args":{"count":107,"avg ms":0}},{"pid":35711,"tid":35725,"ph":"X","ts":0,"dur":13485,"name":"Total InstantiateFunction","args":{"count":64,"avg ms":0}},{"pid":35711,"tid":35726,"ph":"X","ts":0,"dur":9699,"name":"Total PerformPendingInstantiations","args":{"count":1,"avg ms":9}},{"pid":35711,"tid":35727,"ph":"X","ts":0,"dur":1311,"name":"Total DebugType","args":{"count":2109,"avg ms":0}},{"pid":35711,"tid":35728,"ph":"X","ts":0,"dur":1052,"name":"Total Optimizer","args":{"count":1,"avg ms":1}},{"pid":35711,"tid":35729,"ph":"X","ts":0,"dur":969,"name":"Total EvaluateAsRValue","args":{"count":1216,"avg ms":0}},{"pid":35711,"tid":35730,"ph":"X","ts":0,"dur":883,"name":"Total EvaluateForOverflow","args":{"count":813,"avg ms":0}},{"pid":35711,"tid":35731,"ph":"X","ts":0,"dur":828,"name":"Total AlwaysInlinerPass","args":{"count":1,"avg ms":0}},{"pid":35711,"tid":35732,"ph":"X","ts":0,"dur":773,"name":"Total EvaluateAsConstantExpr","args":{"count":934,"avg ms":0}},{"pid":35711,"tid":35733,"ph":"X","ts":0,"dur":722,"name":"Total EvaluateAsInitializer","args":{"count":501,"avg ms":0}},{"pid":35711,"tid":35734,"ph":"X","ts":0,"dur":442,"name":"Total EvaluateAsInt","args":{"count":867,"avg ms":0}},{"pid":35711,"tid":35735,"ph":"X","ts":0,"dur":377,"name":"Total isPotentialConstantExpr","args":{"count":153,"avg ms":0}},{"pid":35711,"tid":35736,"ph":"X","ts":0,"dur":220,"name":"Total DebugGlobalVariable","args":{"count":50,"avg ms":0}},{"pid":35711,"tid":35737,"ph":"X","ts":0,"dur":214,"name":"Total ModuleToFunctionPassAdaptor","args":{"count":1,"avg ms":0}},{"pid":35711,"tid":35738,"ph":"X","ts":0,"dur":212,"name":"Total AAManager","args":{"count":3,"avg ms":0}},{"pid":35711,"tid":35739,"ph":"X","ts":0,"dur":202,"name":"Total BasicAA","args":{"count":3,"avg ms":0}},{"pid":35711,"tid":35740,"ph":"X","ts":0,"dur":202,"name":"Total AssumptionAnalysis","args":{"count":4,"avg ms":0}},{"pid":35711,"tid":35741,"ph":"X","ts":0,"dur":199,"name":"Total TargetIRAnalysis","args":{"count":4,"avg ms":0}},{"pid":35711,"tid":35742,"ph":"X","ts":0,"dur":162,"name":"Total AnnotationRemarksPass","args":{"count":202,"avg ms":0}},{"pid":35711,"tid":35743,"ph":"X","ts":0,"dur":133,"name":"Total EvaluateAsBooleanCondition","args":{"count":88,"avg ms":0}},{"pid":35711,"tid":35744,"ph":"X","ts":0,"dur":67,"name":"Total BlockFrequencyAnalysis","args":{"count":4,"avg ms":0}},{"pid":35711,"tid":35745,"ph":"X","ts":0,"dur":59,"name":"Total TargetLibraryAnalysis","args":{"count":206,"avg ms":0}},{"pid":35711,"tid":35746,"ph":"X","ts":0,"dur":53,"name":"Total BranchProbabilityAnalysis","args":{"count":4,"avg ms":0}},{"pid":35711,"tid":35747,"ph":"X","ts":0,"dur":50,"name":"Total isIntegerConstantExpr","args":{"count":73,"avg ms":0}},{"pid":35711,"tid":35748,"ph":"X","ts":0,"dur":30,"name":"Total DebugConstGlobalVariable","args":{"count":21,"avg ms":0}},{"pid":35711,"tid":35749,"ph":"X","ts":0,"dur":19,"name":"Total EvaluateAsFloat","args":{"count":10,"avg ms":0}},{"pid":35711,"tid":35750,"ph":"X","ts":0,"dur":16,"name":"Total LoopAnalysis","args":{"count":4,"avg ms":0}},{"pid":35711,"tid":35751,"ph":"X","ts":0,"dur":9,"name":"Total EvaluateKnownConstInt","args":{"count":67,"avg ms":0}},{"pid":35711,"tid":35752,"ph":"X","ts":0,"dur":9,"name":"Total PostDominatorTreeAnalysis","args":{"count":4,"avg ms":0}},{"pid":35711,"tid":35753,"ph":"X","ts":0,"dur":7,"name":"Total DominatorTreeAnalysis","args":{"count":4,"avg ms":0}},{"pid":35711,"tid":35754,"ph":"X","ts":0,"dur":2,"name":"Total CoroConditionalWrapper","args":{"count":1,"avg ms":0}},{"pid":35711,"tid":35755,"ph":"X","ts":0,"dur":1,"name":"Total ProfileSummaryAnalysis","args":{"count":1,"avg ms":0}},{"pid":35711,"tid":35756,"ph":"X","ts":0,"dur":0,"name":"Total OuterAnalysisManagerProxy<AnalysisManager<Module>, Function>","args":{"count":3,"avg ms":0}},{"pid":35711,"tid":35757,"ph":"X","ts":0,"dur":0,"name":"Total TypeBasedAA","args":{"count":3,"avg ms":0}},{"pid":35711,"tid":35758,"ph":"X","ts":0,"dur":0,"name":"Total InnerAnalysisManagerProxy<AnalysisManager<Function>, Module>","args":{"count":2,"avg ms":0}},{"pid":35711,"tid":35759,"ph":"X","ts":0,"dur":0,"name":"Total ScopedNoAliasAA","args":{"count":3,"avg ms":0}},{"cat":"","pid":35711,"tid":35711,"ts":0,"ph":"M","name":"process_name","args":{"name":"clang++"}},{"cat":"","pid":35711,"tid":35711,"ts":0,"ph":"M","name":"thread_name","args":{"name":"clang++"}}],"beginningOfTime":1731629094904756}